[
    {
        "_id": "5f783b33e3dc5eaf0ebc076b",
        "semester": "T-1, L-1 (33th)",
        "section": "A",
        "student": "40",
        "courses": [
            {
                "credit": "3",
                "code": "SE111",
                "name": "Computer Fundamentals (A)",
                "teacher": [
                    {
                        "initial": "KBB",
                        "section": "A"
                    },
                    {
                        "initial": "MSI",
                        "section": "B"
                    }
                ]
            },
            {
                "credit": "1",
                "code": "SE112",
                "name": "Computer Fundamentals Lab (A)",
                "teacher": [
                    {
                        "initial": "KBB",
                        "section": "A"
                    },
                    {
                        "initial": "MSI",
                        "section": "B"
                    }
                ]
            }
        ]
    }
]
